setup.py
hmd_dbt_pbt/Binomialdistribution.py
hmd_dbt_pbt/Gaussiandistribution.py
hmd_dbt_pbt/Generaldistribution.py
hmd_dbt_pbt/__init__.py
hmd_dbt_pbt.egg-info/PKG-INFO
hmd_dbt_pbt.egg-info/SOURCES.txt
hmd_dbt_pbt.egg-info/dependency_links.txt
hmd_dbt_pbt.egg-info/not-zip-safe
hmd_dbt_pbt.egg-info/top_level.txt