Metadata-Version: 2.1
Name: hmd-dbt-pbt
Version: 1.2
Summary: Gaussian and Binomial distributions
Home-page: UNKNOWN
Author: Ahmed Limem
Author-email: ahmed.limem@etudiant-enit.utm.tn
License: UNKNOWN
Platform: UNKNOWN
